sprngbk_de_toolkit/__init__.py
sprngbk_de_toolkit/main.py
sprngbk_de_toolkit/vm.py
sprngbk_de_toolkit-0.1.0.dist-info/METADATA
sprngbk_de_toolkit-0.1.0.dist-info/WHEEL
sprngbk_de_toolkit-0.1.0.dist-info/entry_points.txt
sprngbk_de_toolkit-0.1.0.dist-info/RECORD
